{"ARealmRecorded":948,"AccurateCountDown":880,"AdventurerInNeed":3123,"AetherSenseRedux":440,"AutoVisor":1361,"BetterPartyFinder":3235,"BigPlayerDebuffs":6792,"BurntToast":1195,"CharacterPanelRefined":8827,"ChatAlerts":673,"ChatBubbles":14506,"ChatCoordinates":4123,"ChillFrames":1143,"Compass":2479,"CurrencyAlert":1782,"DailyDuty":4831,"Dalamud.FindAnything":1357,"Dalamud.FullscreenCutscenes":374,"Dalamud.LoadingImage":5881,"DamageInfoPlugin":4767,"DeathRecap":6429,"DeepDungeonDex":4873,"DelvUI":7871,"DeviceChangeFix":327,"EasyEyes":4992,"EnemyListDebuffs":2091,"EngageTimer":4586,"FPSPlugin":8580,"FauxHollowsSolver":6662,"FlyTextFilter":986,"GatherBuddy":4706,"Glamaholic":3426,"Globetrotter":17521,"GoodMemory":15432,"HarpHero":4831,"Housemate":3781,"HuntBuddy":4139,"ItemSearchPlugin":6000,"JobBars":10971,"JobIcons":7726,"Kapture":5357,"MOAction":5034,"MPTickBar":3406,"MacroChain":4368,"MapLinker":2457,"MarketBoardPlugin":18527,"MiniCactpotSolver":17389,"NamePlateDebuffs":1071,"Namingway":1164,"NeatNoter":1880,"NoTankYou":2415,"NotificationMaster":2557,"OBSPlugin":571,"OopsAllLalafells":5640,"PartyIcons":2196,"PeepingTom":9061,"PennyPincher":13094,"PingPlugin":8769,"PixelPerfect":12424,"PlayerTags":1489,"PrefPro":369,"PriceCheck":11957,"QoLBar":4150,"Quest Map":2478,"QuestAWAY":1868,"ReadyCheckHelper":2234,"RepairMe":2701,"Reset enmity command":1544,"RezPls":6371,"SimpleTweaksPlugin":21412,"SlideCastPlugin":1595,"SonarPlugin":55725,"SoundFilter":749,"SoundSetter":764,"StarlightBreaker":14637,"TeleporterPlugin":5461,"TheGreatSeparator":920,"TitleEdit":1463,"Tourist":7834,"TriadBuddy":12621,"VFXEditor":2358,"Visibility":4456,"WaymarkPresetPlugin":4369,"WhatDidYouSay":757,"WheresWOLdo":3197,"WinTitle":1008,"XIVChat":1107,"XIVCombo":9642,"faderPlugin":1250,"orchestrion":3364,"owofy":1487,"NoKillPlugin":9287}