{"ARealmRecorded":750,"AccurateCountDown":880,"AdventurerInNeed":2953,"AetherSenseRedux":402,"AutoVisor":1291,"BetterPartyFinder":3082,"BigPlayerDebuffs":6226,"BurntToast":1115,"CharacterPanelRefined":7917,"ChatAlerts":581,"ChatBubbles":13927,"ChatCoordinates":3921,"ChillFrames":993,"Compass":2323,"CurrencyAlert":1489,"DailyDuty":4473,"Dalamud.FindAnything":1233,"Dalamud.FullscreenCutscenes":305,"Dalamud.LoadingImage":5674,"DamageInfoPlugin":4553,"DeathRecap":5665,"DeepDungeonDex":4569,"DelvUI":7497,"DeviceChangeFix":280,"EasyEyes":4688,"EnemyListDebuffs":1861,"EngageTimer":4271,"FPSPlugin":8134,"FauxHollowsSolver":6199,"FlyTextFilter":919,"GatherBuddy":4133,"Glamaholic":3221,"Globetrotter":16547,"GoodMemory":14701,"HarpHero":4492,"Housemate":3504,"HuntBuddy":3678,"ItemSearchPlugin":5744,"JobBars":10477,"JobIcons":7349,"Kapture":5118,"MOAction":4819,"MPTickBar":3171,"MacroChain":4149,"MapLinker":2369,"MarketBoardPlugin":17621,"MiniCactpotSolver":16416,"NamePlateDebuffs":906,"Namingway":1122,"NeatNoter":1778,"NoTankYou":2089,"NotificationMaster":2405,"OBSPlugin":517,"OopsAllLalafells":5385,"PartyIcons":1858,"PeepingTom":8604,"PennyPincher":12496,"PingPlugin":8459,"PixelPerfect":11769,"PlayerTags":1183,"PrefPro":346,"PriceCheck":11331,"QoLBar":3891,"Quest Map":2360,"QuestAWAY":1787,"ReadyCheckHelper":2060,"RepairMe":2570,"Reset enmity command":1450,"RezPls":6106,"SimpleTweaksPlugin":20575,"SlideCastPlugin":1595,"SonarPlugin":52404,"SoundFilter":721,"SoundSetter":694,"StarlightBreaker":13844,"TeleporterPlugin":5231,"TheGreatSeparator":863,"TitleEdit":1411,"Tourist":7457,"TriadBuddy":11875,"VFXEditor":2237,"Visibility":4182,"WaymarkPresetPlugin":4160,"WhatDidYouSay":654,"WheresWOLdo":2936,"WinTitle":966,"XIVChat":1047,"XIVCombo":9174,"faderPlugin":1064,"orchestrion":3251,"owofy":1307,"NoKillPlugin":9168}