{"AccurateCountDown": 880, "AetherSense": 1092, "ChatBubbles": 13592, "OopsAllLalafells": 5260, "QoLBar": 3770, "Tourist": 7274, "PeepingTom": 8356, "SoundSetter": 655, "StarlightBreaker": 13513, "MacroRecursion": 609, "Dalamud.LoadingImage": 5564, "PlayerTrack": 552, "PriceCheck": 11036, "Globetrotter": 16016, "MOAction": 4723, "FPSPlugin": 7881, "VFXEditor": 2186, "SimpleTweaksPlugin": 20053, "EasyEyes": 4589, "Dalamud.RichPresence": 140, "RemindMe": 2239, "TitleEdit": 1390, "Visibility": 4067, "ItemSearchPlugin": 5573, "IMEPlugin": 689, "PennyPincher": 12108, "MarketBoardPlugin": 17149, "GoodMemory": 14182, "WaymarkPresetPlugin": 4081, "TeleporterPlugin": 5060, "GatherBuddy": 3851, "Kapture": 4999, "PingPlugin": 8325, "PixelPerfect": 11340, "JobIcons": 7189, "BetterPartyFinder": 2992, "SlideCast": 1328, "RezPls": 5974, "DamageInfoPlugin": 4439, "MPTimer": 454, "XIVCombo": 8958, "Housemate": 3413, "orchestrion": 3187, "ChatCoordinates": 3807, "WinTitle": 949, "MapLinker": 2308, "SkillSwap": 365, "SoundFilter": 704, "BrowserHost.Plugin": 1, "DeepDungeonDex": 4444, "TextToTalk": 232, "JobBars": 10195, "TriadBuddy": 11438, "EngageTimer": 4093, "MiniCactpotSolver": 15849, "Namingway": 1096, "XIVChat": 1013, "AutoVisor": 1238, "Quest Map": 2281, "Reset enmity command": 1407, "TheGreatSeparator": 840, "NeatNoter": 1729, "DelvUI": 7293, "SlideCastPlugin": 1595, "BurntToast": 1059, "Compass": 2266, "FlyTextFilter": 886, "PartyListLayout": 495, "NoKillPlugin": 9155, "RepairMe": 2501, "WheresWOLdo": 2819, "NotificationMaster": 2337, "QuestAWAY": 1737, "FauxHollowsSolver": 5978, "MacroChain": 4012, "AdventurerInNeed": 2859, "HarpHero": 4341, "PrefPro": 337, "Glamaholic": 3106, "SonarPlugin": 48052, "OBSPlugin": 489, "ReadyCheckHelper": 1973, "EnemyListDebuffs": 1753, "BigPlayerDebuffs": 5911, "Dalamud.FindAnything": 1177, "PlayerTags": 1068, "MPTickBar": 3048, "HuntBuddy": 3449, "PartyIcons": 1724, "CurrencyAlert": 1366, "ChillFrames": 916, "DailyDuty": 4243, "AetherSenseRedux": 372, "CharacterPanelRefined": 7312, "faderPlugin": 972, "NamePlateDebuffs": 836, "ChatAlerts": 515, "DeviceChangeFix": 247, "NoTankYou": 1876, "owofy": 1226, "Dalamud.FullscreenCutscenes": 274, "WhatDidYouSay": 615, "DeathRecap": 5343, "ARealmRecorded": 599}