{"ARealmRecorded":748,"AccurateCountDown":880,"AdventurerInNeed":2953,"AetherSenseRedux":402,"AutoVisor":1291,"BetterPartyFinder":3082,"BigPlayerDebuffs":6226,"BurntToast":1115,"CharacterPanelRefined":7910,"ChatAlerts":579,"ChatBubbles":13926,"ChatCoordinates":3921,"ChillFrames":993,"Compass":2322,"CurrencyAlert":1488,"DailyDuty":4472,"Dalamud.FindAnything":1233,"Dalamud.FullscreenCutscenes":304,"Dalamud.LoadingImage":5672,"DamageInfoPlugin":4553,"DeathRecap":5665,"DeepDungeonDex":4568,"DelvUI":7496,"DeviceChangeFix":280,"EasyEyes":4687,"EnemyListDebuffs":1861,"EngageTimer":4271,"FPSPlugin":8133,"FauxHollowsSolver":6197,"FlyTextFilter":919,"GatherBuddy":4132,"Glamaholic":3219,"Globetrotter":16544,"GoodMemory":14697,"HarpHero":4491,"Housemate":3503,"HuntBuddy":3677,"ItemSearchPlugin":5744,"JobBars":10475,"JobIcons":7348,"Kapture":5118,"MOAction":4819,"MPTickBar":3171,"MacroChain":4148,"MapLinker":2369,"MarketBoardPlugin":17617,"MiniCactpotSolver":16409,"NamePlateDebuffs":906,"Namingway":1122,"NeatNoter":1777,"NoTankYou":2089,"NotificationMaster":2405,"OBSPlugin":516,"OopsAllLalafells":5384,"PartyIcons":1858,"PeepingTom":8602,"PennyPincher":12491,"PingPlugin":8459,"PixelPerfect":11766,"PlayerTags":1182,"PrefPro":346,"PriceCheck":11330,"QoLBar":3890,"Quest Map":2359,"QuestAWAY":1786,"ReadyCheckHelper":2059,"RepairMe":2570,"Reset enmity command":1450,"RezPls":6106,"SimpleTweaksPlugin":20565,"SlideCastPlugin":1595,"SonarPlugin":52214,"SoundFilter":721,"SoundSetter":694,"StarlightBreaker":13840,"TeleporterPlugin":5230,"TheGreatSeparator":863,"TitleEdit":1411,"Tourist":7456,"TriadBuddy":11872,"VFXEditor":2236,"Visibility":4181,"WaymarkPresetPlugin":4160,"WhatDidYouSay":654,"WheresWOLdo":2935,"WinTitle":966,"XIVChat":1046,"XIVCombo":9173,"faderPlugin":1062,"orchestrion":3251,"owofy":1307,"NoKillPlugin":9167}