{"AudibleCharacterStatus":381,"BetterPartyFinder":3811,"BigPlayerDebuffs":10410,"CharacterPanelRefined":10842,"ChatAlerts":1108,"ChatBubbles":17402,"ChatCoordinates":5282,"ChillFrames":1962,"CurrencyAlert":3076,"DailyDuty":7280,"Dalamud.FullscreenCutscenes":786,"Dalamud.LoadingImage":7629,"DeepDungeonDex":6146,"DelvUI":8536,"Distance":607,"EnemyListDebuffs":3566,"EnmityHp":765,"FPSPlugin":10985,"FlashOnTell":192,"GatherBuddy":6921,"Glamaholic":4604,"Globetrotter":26310,"GoodMemory":18151,"Housemate":5259,"ItemSearchPlugin":8033,"JobBars":12962,"MPTickBar":4090,"MacroChain":6367,"MapLinker":3187,"MarketBoardPlugin":24028,"Mini":148,"MiniCactpotSolver":22870,"Namingway":1303,"NoTankYou":4317,"OBSPlugin":762,"PennyPincher":16843,"PingPlugin":10745,"PixelPerfect":15437,"ProperHousing":888,"QoLBar":4829,"QuestAWAY":2430,"ReadyCheckHelper":3461,"RepairMe":3181,"Reset enmity command":2184,"RezPls":8384,"SimpleTweaksPlugin":27476,"SonarPlugin":61395,"SoundFilter":871,"SoundSetter":993,"StarlightBreaker":16198,"TeleporterPlugin":7563,"TextToTalk":343,"TitleEdit":1641,"Tourist":10010,"Visibility":8326,"WaymarkPresetPlugin":5662,"Weatherman":149,"WheresWOLdo":4028,"WinTitle":1192,"orchestrion":4550,"ARealmRecorded":1164,"Accountant":370,"AdaptiveHud":48,"AdventurerInNeed":3628,"AetherCompass":103,"BatteryGauge":41,"Browsingway":88,"BurntToast":1302,"ChatTwo":214,"ChatTyper":39,"Compass":2645,"Dalamud.CharacterSync":101,"Dalamud.DiscordBridge":18,"Dalamud.FindAnything":1569,"Dalamud.RichPresence":183,"DalamudVox":0,"DamageInfoPlugin":5414,"DeathRecap":7764,"DeviceChangeFix":443,"EasyEyes":5351,"EngageTimer":5660,"ExpandedSearchInfo":49,"ExtraChat":24,"FCNameColor":44,"FantasyPlayer.Dalamud":25,"FauxHollowsSolver":8063,"Ffxiv2Mqtt":6,"FlyTextFilter":1082,"FullscreenToggle":0,"GearsetHelperPlugin":46,"GentleTouch":24,"HUDManager":59,"HarpHero":5167,"HuntBuddy":4984,"InventoryTools":88,"ItemVendorLocation":172,"JustBackup":144,"Kapture":5761,"KingdomHeartsPlugin":112,"MOAction":5542,"MimicryHelper":62,"NamePlateDebuffs":1344,"NeatNoter":2097,"NextUIPlugin":59,"NoKillPlugin":10835,"NoSoliciting":38,"NotificationMaster":2848,"PartyIcons":3393,"PatMe":75,"PeepingTom":10005,"PlayerTags":1836,"PlayerTrack":622,"PrefPro":438,"PriceCheck":12854,"Quest Map":2812,"QuoteOfTheLobby":10,"Redirect":146,"RemotePartyFinder":12,"ResLogger2.Plugin":11,"ResetAudio":46,"SillyChat":13,"SkillDisplay":128,"SkillSwap":428,"Snooper":18,"StackSellPrice":52,"SupineSnail.JobGaugeAdjustments":208,"TPie":49,"TabTab":0,"TextBoxStyler":15,"TheGreatSeparator":1039,"TheHeartOfTheParty":24,"TidyChat":30,"Tippy":109,"TriadBuddy":14408,"UsedName":29,"VFXEditor":2516,"Waitingway.Dalamud":29,"WhatDidYouSay":1108,"WhereAmIAgain":106,"WondrousTailsSolver":300,"Wordsmith":18,"XIVChat":1173,"XIVCombo":10698,"XIVDeck.FFXIVPlugin":37,"XIVLogger":93,"ZodiacBuddy":137,"autoSweep":127,"cl_showpos":79,"faderPlugin":1449,"owofy":1673}