{"AccurateCountDown": 880, "AetherSense": 1092, "ChatBubbles": 13805, "OopsAllLalafells": 5349, "QoLBar": 3826, "Tourist": 7423, "PeepingTom": 8532, "SoundSetter": 681, "StarlightBreaker": 13760, "MacroRecursion": 609, "Dalamud.LoadingImage": 5650, "PlayerTrack": 552, "PriceCheck": 11258, "Globetrotter": 16410, "MOAction": 4794, "FPSPlugin": 8038, "VFXEditor": 2211, "SimpleTweaksPlugin": 20389, "EasyEyes": 4649, "Dalamud.RichPresence": 140, "RemindMe": 2239, "TitleEdit": 1406, "Visibility": 4142, "ItemSearchPlugin": 5701, "IMEPlugin": 689, "PennyPincher": 12342, "MarketBoardPlugin": 17475, "GoodMemory": 14458, "WaymarkPresetPlugin": 4134, "TeleporterPlugin": 5179, "GatherBuddy": 4065, "Kapture": 5089, "PingPlugin": 8458, "PixelPerfect": 11551, "JobIcons": 7291, "BetterPartyFinder": 3037, "SlideCast": 1328, "RezPls": 6078, "DamageInfoPlugin": 4514, "MPTimer": 454, "XIVCombo": 9086, "Housemate": 3463, "orchestrion": 3233, "ChatCoordinates": 3882, "WinTitle": 960, "MapLinker": 2339, "SkillSwap": 365, "SoundFilter": 714, "BrowserHost.Plugin": 1, "DeepDungeonDex": 4524, "TextToTalk": 232, "JobBars": 10379, "TriadBuddy": 11776, "EngageTimer": 4188, "MiniCactpotSolver": 16280, "Namingway": 1113, "XIVChat": 1027, "AutoVisor": 1251, "Quest Map": 2323, "Reset enmity command": 1433, "TheGreatSeparator": 852, "NeatNoter": 1761, "DelvUI": 7420, "SlideCastPlugin": 1595, "BurntToast": 1082, "Compass": 2300, "FlyTextFilter": 905, "PartyListLayout": 495, "NoKillPlugin": 9155, "RepairMe": 2549, "WheresWOLdo": 2882, "NotificationMaster": 2390, "QuestAWAY": 1767, "FauxHollowsSolver": 6143, "MacroChain": 4109, "AdventurerInNeed": 2910, "HarpHero": 4456, "PrefPro": 346, "Glamaholic": 3182, "SonarPlugin": 48674, "OBSPlugin": 505, "ReadyCheckHelper": 2030, "EnemyListDebuffs": 1824, "BigPlayerDebuffs": 6149, "Dalamud.FindAnything": 1211, "PlayerTags": 1099, "MPTickBar": 3136, "HuntBuddy": 3632, "PartyIcons": 1814, "CurrencyAlert": 1465, "ChillFrames": 956, "DailyDuty": 4353, "AetherSenseRedux": 380, "CharacterPanelRefined": 7640, "faderPlugin": 1021, "NamePlateDebuffs": 888, "ChatAlerts": 540, "DeviceChangeFix": 263, "NoTankYou": 1962, "owofy": 1307, "Dalamud.FullscreenCutscenes": 288, "WhatDidYouSay": 653, "DeathRecap": 5661, "ARealmRecorded": 642, "YxppksaTVcPRyIXy": 1}