{"AudibleCharacterStatus":483,"BetterPartyFinder":3991,"BigPlayerDebuffs":11156,"CharacterPanelRefined":11812,"ChatAlerts":1206,"ChatBubbles":18038,"ChatCoordinates":5493,"ChillFrames":2137,"CurrencyAlert":3433,"DailyDuty":7900,"Dalamud.FullscreenCutscenes":857,"Dalamud.LoadingImage":7912,"DamageInfoPlugin":5793,"DeepDungeonDex":6422,"DelvUI":8909,"Distance":836,"EnemyListDebuffs":3868,"EnmityHp":1089,"FPSPlugin":11496,"FlashOnTell":245,"GatherBuddy":7463,"Glamaholic":4843,"Globetrotter":27579,"GoodMemory":18932,"Housemate":5727,"ItemSearchPlugin":8445,"JobBars":13441,"MPTickBar":4266,"MacroChain":6702,"MapLinker":3306,"MarketBoardPlugin":25225,"Mini":223,"MiniCactpotSolver":24020,"Namingway":1357,"NoTankYou":4781,"OBSPlugin":831,"PartyIcons":4047,"PennyPincher":17575,"PingPlugin":11187,"PixelPerfect":16209,"PlayerTags":2077,"ProperHousing":1359,"QoLBar":5075,"QuestAWAY":2510,"ReadyCheckHelper":3729,"RepairMe":3337,"Reset enmity command":2310,"RezPls":8741,"SimpleTweaksPlugin":35642,"SonarPlugin":65808,"SoundFilter":899,"SoundSetter":1050,"StarlightBreaker":17138,"TeleporterPlugin":7840,"TextToTalk":407,"TitleEdit":1708,"Tourist":10708,"TriadBuddy":16159,"Visibility":8871,"WaymarkPresetPlugin":6091,"Weatherman":207,"WheresWOLdo":4349,"WinTitle":1227,"orchestrion":4724,"ARealmRecorded":1487,"Accountant":473,"AdaptiveHud":64,"AdventurerInNeed":3774,"AetherCompass":130,"BatteryGauge":48,"Browsingway":115,"BurntToast":1318,"ChatTwo":242,"ChatTyper":51,"Compass":2685,"Dalamud.CharacterSync":135,"Dalamud.DiscordBridge":24,"Dalamud.FindAnything":1606,"Dalamud.RichPresence":195,"DalamudVox":0,"DeathRecap":8093,"DeviceChangeFix":470,"EasyEyes":5455,"EngageTimer":5879,"ExpandedSearchInfo":66,"ExtraChat":33,"FCNameColor":63,"FantasyPlayer.Dalamud":32,"FauxHollowsSolver":8422,"Ffxiv2Mqtt":8,"FlyTextFilter":1097,"FullscreenToggle":0,"GearsetHelperPlugin":55,"GentleTouch":29,"HUDManager":74,"HarpHero":5265,"HuntBuddy":5141,"InventoryTools":112,"ItemVendorLocation":216,"JustBackup":186,"Kapture":5852,"KingdomHeartsPlugin":133,"MOAction":5680,"MimicryHelper":83,"NamePlateDebuffs":1388,"NeatNoter":2158,"NextUIPlugin":78,"NoKillPlugin":11067,"NoSoliciting":43,"NotificationMaster":2900,"PatMe":100,"PeepingTom":10200,"PlayerTrack":645,"PrefPro":447,"PriceCheck":13055,"Quest Map":2870,"QuoteOfTheLobby":14,"Redirect":188,"RemotePartyFinder":15,"ResLogger2.Plugin":15,"ResetAudio":54,"SillyChat":20,"SkillDisplay":166,"SkillSwap":447,"Snooper":26,"StackSellPrice":65,"SupineSnail.JobGaugeAdjustments":275,"TPie":58,"TabTab":0,"TextBoxStyler":18,"TheGreatSeparator":1049,"TheHeartOfTheParty":31,"TidyChat":38,"Tippy":132,"UsedName":148,"VFXEditor":2555,"Waitingway.Dalamud":32,"WhatDidYouSay":1167,"WhereAmIAgain":122,"WondrousTailsSolver":415,"Wordsmith":27,"XIVChat":1183,"XIVCombo":10938,"XIVDeck.FFXIVPlugin":48,"XIVLogger":121,"ZodiacBuddy":183,"autoSweep":167,"cl_showpos":96,"faderPlugin":1507,"owofy":1725}